tgcrypto.cp311-win_amd64.pyd
tests/__init__.py
tests/cbc/__init__.py
tests/cbc/test_cbc.py
tests/ctr/__init__.py
tests/ctr/test_ctr.py
tests/ige/__init__.py
tests/ige/test_ige.py
TgCrypto_pyroblack-1.2.6.dist-info/COPYING
TgCrypto_pyroblack-1.2.6.dist-info/COPYING.lesser
TgCrypto_pyroblack-1.2.6.dist-info/METADATA
TgCrypto_pyroblack-1.2.6.dist-info/NOTICE
TgCrypto_pyroblack-1.2.6.dist-info/WHEEL
TgCrypto_pyroblack-1.2.6.dist-info/top_level.txt
TgCrypto_pyroblack-1.2.6.dist-info/RECORD
