Metadata-Version: 2.1
Name: TgCrypto-pyroblack
Version: 1.2.6
Summary: Fast and Portable Cryptography Extension Library for pyroblack
Home-page: https://github.com/eyMarv
Download-URL: https://github.com/eyMarv/tgcrypto-pyroblack/releases/latest
Author: eyMarv
Author-email: eyMarv07@gmail.com
License: LGPLv3+
Project-URL: Tracker, https://github.com/eyMarv/tgcrypto-pyroblack/issues
Project-URL: Community, https://t.me/OpenFileZ
Project-URL: Source, https://github.com/eyMarv/tgcrypto-pyroblack
Project-URL: Documentation, https://eyMarv.github.io/pyroblack-docs
Keywords: pyrogram pyroblack telegram crypto cryptography encryption mtproto extension library aes
Classifier: Development Status :: 5 - Production/Stable
Classifier: Intended Audience :: Developers
Classifier: License :: OSI Approved :: GNU Lesser General Public License v3 or later (LGPLv3+)
Classifier: Operating System :: OS Independent
Classifier: Programming Language :: C
Classifier: Programming Language :: Python
Classifier: Programming Language :: Python :: 3
Classifier: Programming Language :: Python :: 3.8
Classifier: Programming Language :: Python :: 3.9
Classifier: Programming Language :: Python :: 3.10
Classifier: Programming Language :: Python :: 3.11
Classifier: Programming Language :: Python :: 3.12
Classifier: Programming Language :: Python :: Implementation
Classifier: Programming Language :: Python :: Implementation :: CPython
Classifier: Programming Language :: Python :: Implementation :: PyPy
Classifier: Topic :: Security
Classifier: Topic :: Security :: Cryptography
Classifier: Topic :: Internet
Classifier: Topic :: Communications
Classifier: Topic :: Communications :: Chat
Classifier: Topic :: Software Development :: Libraries
Classifier: Topic :: Software Development :: Libraries :: Python Modules
Requires-Python: ~=3.8
License-File: COPYING
License-File: COPYING.lesser
License-File: NOTICE
